{
  "metadata": {
    "report_key": "country-pair-no-price-poland-to-spain",
    "report_type": "country_pair_no_price",
    "generated_at": "2026-07-08T09:28:24.458Z",
    "period": {
      "date_from": "2026-06-01",
      "date_to": "2026-07-01"
    },
    "filters": {
      "origin_country_name": "Poland",
      "destination_country_name": "Spain",
      "has_price": false,
      "limit": 30
    }
  },
  "summary": {
    "rows": 30,
    "searches_total": 1137,
    "searches_without_price": 965
  },
  "data": [
    {
      "origin_city_name": "Warsaw",
      "destination_city_name": "Alicante",
      "origin_country_name": "Poland",
      "destination_country_name": "Spain",
      "count": 115
    },
    {
      "origin_city_name": "Warsaw",
      "destination_city_name": "Madrid",
      "origin_country_name": "Poland",
      "destination_country_name": "Spain",
      "count": 75
    },
    {
      "origin_city_name": "Warsaw",
      "destination_city_name": "Barcelona",
      "origin_country_name": "Poland",
      "destination_country_name": "Spain",
      "count": 67
    },
    {
      "origin_city_name": "Warsaw",
      "destination_city_name": "Valencia",
      "origin_country_name": "Poland",
      "destination_country_name": "Spain",
      "count": 59
    },
    {
      "origin_city_name": "Krakow",
      "destination_city_name": "Alicante",
      "origin_country_name": "Poland",
      "destination_country_name": "Spain",
      "count": 43
    },
    {
      "origin_city_name": "Krakow",
      "destination_city_name": "Valencia",
      "origin_country_name": "Poland",
      "destination_country_name": "Spain",
      "count": 42
    },
    {
      "origin_city_name": "Krakow",
      "destination_city_name": "Barcelona",
      "origin_country_name": "Poland",
      "destination_country_name": "Spain",
      "count": 41
    },
    {
      "origin_city_name": "Lodz",
      "destination_city_name": "Valencia",
      "origin_country_name": "Poland",
      "destination_country_name": "Spain",
      "count": 33
    },
    {
      "origin_city_name": "Krakow",
      "destination_city_name": "Benidorm",
      "origin_country_name": "Poland",
      "destination_country_name": "Spain",
      "count": 21
    },
    {
      "origin_city_name": "Krakow",
      "destination_city_name": "Málaga",
      "origin_country_name": "Poland",
      "destination_country_name": "Spain",
      "count": 21
    },
    {
      "origin_city_name": "Krakow",
      "destination_city_name": "Madrid",
      "origin_country_name": "Poland",
      "destination_country_name": "Spain",
      "count": 20
    },
    {
      "origin_city_name": "Przemyśl",
      "destination_city_name": "Barcelona",
      "origin_country_name": "Poland",
      "destination_country_name": "Spain",
      "count": 17
    },
    {
      "origin_city_name": "Przemyśl",
      "destination_city_name": "Alicante",
      "origin_country_name": "Poland",
      "destination_country_name": "Spain",
      "count": 16
    },
    {
      "origin_city_name": "Torun",
      "destination_city_name": "Barcelona",
      "origin_country_name": "Poland",
      "destination_country_name": "Spain",
      "count": 16
    },
    {
      "origin_city_name": "Bielsko-Biala",
      "destination_city_name": "Terrassa",
      "origin_country_name": "Poland",
      "destination_country_name": "Spain",
      "count": 14
    },
    {
      "origin_city_name": "Katowice",
      "destination_city_name": "Torrevieja",
      "origin_country_name": "Poland",
      "destination_country_name": "Spain",
      "count": 13
    },
    {
      "origin_city_name": "Warsaw",
      "destination_city_name": "Benidorm",
      "origin_country_name": "Poland",
      "destination_country_name": "Spain",
      "count": 12
    },
    {
      "origin_city_name": "Wroclaw",
      "destination_city_name": "Barcelona",
      "origin_country_name": "Poland",
      "destination_country_name": "Spain",
      "count": 12
    },
    {
      "origin_city_name": "Gdańsk",
      "destination_city_name": "Málaga",
      "origin_country_name": "Poland",
      "destination_country_name": "Spain",
      "count": 11
    },
    {
      "origin_city_name": "Warsaw",
      "destination_city_name": "Zaragoza",
      "origin_country_name": "Poland",
      "destination_country_name": "Spain",
      "count": 11
    },
    {
      "origin_city_name": "Wroclaw",
      "destination_city_name": "Alicante",
      "origin_country_name": "Poland",
      "destination_country_name": "Spain",
      "count": 11
    },
    {
      "origin_city_name": "Gdańsk",
      "destination_city_name": "Madrid",
      "origin_country_name": "Poland",
      "destination_country_name": "Spain",
      "count": 10
    },
    {
      "origin_city_name": "Warsaw",
      "destination_city_name": "Gijón",
      "origin_country_name": "Poland",
      "destination_country_name": "Spain",
      "count": 10
    },
    {
      "origin_city_name": "Warsaw",
      "destination_city_name": "Torrevieja",
      "origin_country_name": "Poland",
      "destination_country_name": "Spain",
      "count": 10
    },
    {
      "origin_city_name": "Przemyśl",
      "destination_city_name": "Málaga",
      "origin_country_name": "Poland",
      "destination_country_name": "Spain",
      "count": 9
    },
    {
      "origin_city_name": "Bielsko-Biala",
      "destination_city_name": "Valencia",
      "origin_country_name": "Poland",
      "destination_country_name": "Spain",
      "count": 8
    },
    {
      "origin_city_name": "Katowice",
      "destination_city_name": "Barcelona",
      "origin_country_name": "Poland",
      "destination_country_name": "Spain",
      "count": 8
    },
    {
      "origin_city_name": "Krakow",
      "destination_city_name": "Girona",
      "origin_country_name": "Poland",
      "destination_country_name": "Spain",
      "count": 8
    },
    {
      "origin_city_name": "Przemyśl",
      "destination_city_name": "Valencia",
      "origin_country_name": "Poland",
      "destination_country_name": "Spain",
      "count": 8
    },
    {
      "origin_city_name": "Katowice",
      "destination_city_name": "Alicante",
      "origin_country_name": "Poland",
      "destination_country_name": "Spain",
      "count": 7
    }
  ]
}